{
    "image": {
        "id": 153,
        "width": 414,
        "height": 600,
        "file_name": "010.jpg",
        "license": 0,
        "date_captured": ""
    },
    "annotations": [
        {
            "segmentation": [
                [
                    21,
                    72,
                    378,
                    72,
                    378,
                    549,
                    21,
                    549
                ]
            ],
            "area": 170289,
            "bbox": [
                21,
                72,
                357,
                477
            ],
            "iscrowd": 0,
            "id": 153,
            "image_id": 153,
            "category_id": 4
        }
    ]
}